CHANGES.md
LICENSE
MANIFEST.in
README.md
setup.cfg
setup.py
pl_sandbox_api.egg-info/PKG-INFO
pl_sandbox_api.egg-info/SOURCES.txt
pl_sandbox_api.egg-info/dependency_links.txt
pl_sandbox_api.egg-info/requires.txt
pl_sandbox_api.egg-info/top_level.txt
sandbox_api/__init__.py
sandbox_api/asandbox.py
sandbox_api/enums.py
sandbox_api/exceptions.py
sandbox_api/sandbox.py
sandbox_api/utils.py