Metadata-Version: 2.1
Name: pl-sandbox-api
Version: 1.1.4
Summary: Provide a Python 3 interface to communicate with a sandbox (https://github.com/PremierLangage/sandbox)
Home-page: https://github.com/qcoumes/sandbox-api
Author: Coumes Quentin
Author-email: coumes.quentin@gmail.com
License: UNKNOWN
Platform: UNKNOWN
Classifier: Development Status :: 4 - Beta
Classifier: Intended Audience :: Developers
Classifier: License :: OSI Approved :: MIT License
Classifier: Natural Language :: English
Classifier: Operating System :: POSIX :: Linux
Classifier: Programming Language :: Python :: 3.5
Classifier: Programming Language :: Python :: 3.6
Classifier: Programming Language :: Python :: 3.7
Classifier: Programming Language :: Python :: 3.8
Classifier: Topic :: Software Development :: Libraries :: Python Modules
